multispeq1/__init__.py
multispeq1/node.py
multispeq1/proxy.py
multispeq1/Arduino/library/Multispeq1.zip
multispeq1/Arduino/library/Multispeq1/library.properties
multispeq1/Arduino/library/Multispeq1/src/Multispeq1.h
multispeq1/Arduino/library/Multispeq1/src/Multispeq1/CommandProcessor.h
multispeq1/Arduino/library/Multispeq1/src/Multispeq1/Commands.h
multispeq1/Arduino/library/Multispeq1/src/Multispeq1/Properties.h
multispeq1/Arduino/library/Multispeq1/src/Multispeq1/aligned_alloc.h
multispeq1/Arduino/multispeq1/DAC.cpp
multispeq1/Arduino/multispeq1/DAC.h
multispeq1/Arduino/multispeq1/Node.cpp
multispeq1/Arduino/multispeq1/Node.h
multispeq1/Arduino/multispeq1/NodeCommandProcessor.h
multispeq1/Arduino/multispeq1/PAR.cpp
multispeq1/Arduino/multispeq1/PAR.h
multispeq1/Arduino/multispeq1/RPCBuffer.h
multispeq1/Arduino/multispeq1/RPCBuffer.ht
multispeq1/Arduino/multispeq1/SConscript
multispeq1/Arduino/multispeq1/defines.h
multispeq1/Arduino/multispeq1/eeprom.cpp
multispeq1/Arduino/multispeq1/eeprom.h
multispeq1/Arduino/multispeq1/expr.cpp
multispeq1/Arduino/multispeq1/flasher.cpp
multispeq1/Arduino/multispeq1/flasher.h
multispeq1/Arduino/multispeq1/loop-switch-jz.h
multispeq1/Arduino/multispeq1/loop.cpp
multispeq1/Arduino/multispeq1/multispeq1.ino
multispeq1/Arduino/multispeq1/notes
multispeq1/Arduino/multispeq1/power.txt
multispeq1/Arduino/multispeq1/protocol.jz
multispeq1/Arduino/multispeq1/serial.cpp
multispeq1/Arduino/multispeq1/serial.h
multispeq1/Arduino/multispeq1/util-jz.cpp
multispeq1/Arduino/multispeq1/util.cpp
multispeq1/Arduino/multispeq1/util.h
multispeq1/Arduino/multispeq1/json/JsonArray.cpp
multispeq1/Arduino/multispeq1/json/JsonArray.h
multispeq1/Arduino/multispeq1/json/JsonHashTable.cpp
multispeq1/Arduino/multispeq1/json/JsonHashTable.h
multispeq1/Arduino/multispeq1/json/JsonObjectBase.cpp
multispeq1/Arduino/multispeq1/json/JsonObjectBase.h
multispeq1/Arduino/multispeq1/json/JsonParser.h
multispeq1-0.1.post2.dist-info/DESCRIPTION.rst
multispeq1-0.1.post2.dist-info/METADATA
multispeq1-0.1.post2.dist-info/RECORD
multispeq1-0.1.post2.dist-info/WHEEL
multispeq1-0.1.post2.dist-info/metadata.json
multispeq1-0.1.post2.dist-info/top_level.txt
