Metadata-Version: 2.0
Name: multispeq1
Version: 0.1.post2
Summary: Template project demonstrating use of Arduino base node RPC framework.
Home-page: http://github.com/wheeler-microfluidics/multispeq1.git
Author: Christian Fobel
Author-email: christian@fobel.net
License: GPLv2
Platform: UNKNOWN
Requires-Dist: base-node-rpc (>=0.12.post11)
